nightscout_cli/__init__.py
nightscout_cli/main.py
nightscout_cli-2.0.0.dist-info/METADATA
nightscout_cli-2.0.0.dist-info/WHEEL
nightscout_cli-2.0.0.dist-info/entry_points.txt
nightscout_cli-2.0.0.dist-info/top_level.txt
nightscout_cli-2.0.0.dist-info/RECORD
