Metadata-Version: 2.4
Name: nightscout-cli
Version: 2.0.0
Summary: Command line interface for Nightscout API
Requires-Python: >=3.8
Requires-Dist: requests>=2.25.0
